Workbook

Sheet Assumptions
A1: Monmouth-Robertson Acquisition Analysis
A3: Key Assumptions
A5: Historical Data (Robertson Tool Company)
A6: Year | B6: 1998 | C6: 1999 | D6: 2000 | E6: 2001 | F6: 2002
A7: Sales ($ millions) | B7: 48.5 | C7: 49.1 | D7: 53.7 | E7: 54.8 | F7: 55.3
A8: COGS ($ millions) | B8: 32.6 | C8: 33.1 | D8: 35.9 | E8: 37.2 | F8: 37.9
A9: SG&A ($ millions) | B9: 10.7 | C9: 11.1 | D9: 11.5 | E9: 11.9 | F9: 12.3
A10: Depreciation ($ millions) | B10: 2 | C10: 2.3 | D10: 2.4 | E10: 2.3 | F10: 2.1
A11: Interest Expense ($ millions) | B11: 0.4 | C11: 0.7 | D11: 0.8 | E11: 0.8 | F11: 0.8
A13: Balance Sheet Data (2002) ($ millions)
A14: Cash | B14: 1
A15: Accounts Receivable | B15: 8
A16: Inventories | B16: 18
A17: Other Current Assets | B17: 1
A18: Current Assets | B18: 28
A19: Net Plant and Equipment | B19: 19
A20: Total Assets | B20: 47
A21: Accounts Payable | B21: 2
A22: Other Current Liabilities | B22: 2
A23: Current Liabilities | B23: 4
A24: Long-term Debt | B24: 12
A25: Net Worth | B25: 31
A27: Financial Ratios
A28: Collection Period (days) | B28: 53
A29: Days of Inventory | B29: 173
A30: Sales/Total Assets | B30: 1.18
A31: Debt Capital | B31: 28%
A32: Total Assets/Net Worth | B32: 1.52
A34: Pro-forma Projections ($ millions)
A35: Year | B35: 2003 | C35: 2004 | D35: 2005 | E35: 2006 | F35: 2007
A36: Sales | B36: 58.6 | C36: 62.1 | D36: 65.9 | E36: 69.8 | F36: 69.8
A37: COGS | B37: 39.8 | C37: 41.6 | D37: 43.5 | E37: 45.4 | F37: 45.4
A38: SG&A | B38: 12.3 | C38: 12.4 | D38: 12.5 | E38: 13.3 | F38: 13.3
A39: Depreciation | B39: 2.3 | C39: 2.5 | D39: 2.7 | E39: 2.9 | F39: 2.9
A40: EBIT | B40: 4.2 | C40: 5.6 | D40: 7.2 | E40: 8.2 | F40: 8.2
A41: Tax @ 40% | B41: 1.7 | C41: 2.2 | D41: 2.9 | E41: 3.3 | F41: 3.3
A43: Capital Market Information
A44: 30-Year U.S. Treasury Bonds | B44: 4.10%
A45: U.S. Corporate Bonds Rated AA | B45: 4.52%
A46: U.S. Corporate Bonds Rated A | B46: 5.07%
A47: U.S. Corporate Bonds Rated BBB | B47: 6.07%
A48: U.S. Corporate Bonds Rated BB | B48: 7.96%
A49: Market Risk Premium | B49: 6.00%
A51: Valuation Parameters
A52: Asset Beta | B52: 0.75
A53: Equity Beta | B53: =B52/0.72 -> 1.0416667
A54: Cost of Equity | B54: =B53+(B53*B58) -> 1.0625
A55: Cost of Debt | B55: =B49*(1-0.4) -> 0.036
A56: Tax Rate | B56: 0.4
A57: WACC | B57: 0.0814
A58: Terminal Growth Rate | B58: 0.02
A59: Shares Outstanding | B59: 584000

Sheet FCF
D2: TERMINAL Growth | E2: 0.02 | G2: NWC/Sales | H2: =R10/C10 -> 0.43399638
D3: SALES GROWTH | E3: 0.06
A7: Free Cash Flow Model
A9: Year | C9: Sales | D9: COGS | E9: SG&A | F9: Depreciation | G9: EBIT | H9: Taxes on EBIT | I9: EBIAT | J9: Depreciation | K9: CapEx | L9: AR | M9: Inventory | N9: AP | O9: Operating Cash Flow | P9: Change in Fixed Assets | Q9: NWC | R9: ΔNWC | S9: Free Cash Flow | T9: PV of CF | U9: Discount Factor
A10: 2002 | B10: 0 | C10: 55.3 | D10: 37.9 | E10: 12.3 | F10: 2.1 | G10: =C10-D10-E10-F10 -> 3 | H10: =G10*Assumptions!$B$56 -> 1.2 | I10: =G10-H10 -> 1.8 | J10: =F10 -> 2.1 | K10: 0 | L10: 8 | M10: 18 | N10: 2 | O10: =I10+J10 -> 3.9 | Q10: 24 | R10: 24 | V10: =S10 -> 0
A11: 2003 | B11: 1 | C11: 58.62 | D11: 39.81 | E11: 12.3 | F11: 2.3 | G11: =C11-D11-E11-F11 -> 4.21 | H11: =G11*Assumptions!$B$56 -> 1.684 | I11: =G11-H11 -> 2.526 | J11: =F11 -> 2.3 | K11: -4 | L11: 8.5 | M11: 11.7 | N11: 2.1 | O11: =I11+J11 -> 4.826 | P11: 4 | Q11: =C11*H2 -> 25.440868 | R11: =Q11-Q10 -> 1.440868 | S11: =O11-P11-R11 -> -0.61486799 | T11: =S11/(1+I35)^B11 -> -0.5656553 | U11: =1/(1+Assumptions!$B$57)^'[1]FCF Model'!T11 -> 1 | V11: =S11*U11 -> -0.61486799 | X11: 1
A12: 2004 | B12: 2 | C12: 62.14 | D12: 41.62 | E12: 12.41 | F12: 2.5 | G12: =C12-D12-E12-F12 -> 5.61 | H12: =G12*Assumptions!$B$56 -> 2.244 | I12: =G12-H12 -> 3.366 | J12: =F12 -> 2.5 | K12: -3.5 | L12: 9 | M12: 12.4 | N12: 2.3 | O12: =I12+J12 -> 5.866 | P12: 3.5 | Q12: =C12*H2 -> 26.968535 | R12: =Q12-Q11 -> 1.5276673 | S12: =O12-P12-R12 -> 0.83833273 | T12: =S12/(1+I35)^B12 -> 0.70950649 | U12: =1/(1+Assumptions!$B$57)^'[1]FCF Model'!T12 -> 1 | V12: =S12*U12 -> 0.83833273 | X12: 2
A13: 2005 | B13: 3 | C13: 65.86 | D13: 43.48 | E13: 13.26 | F13: 2.7 | G13: =C13-D13-E13-F13 -> 6.42 | H13: =G13*Assumptions!$B$56 -> 2.568 | I13: =G13-H13 -> 3.852 | J13: =F13 -> 2.7 | K13: -3.6 | L13: 9.6 | M13: 13.2 | N13: 2.4 | O13: =I13+J13 -> 6.552 | P13: 3.6 | Q13: =C13*H2 -> 28.583002 | R13: =Q13-Q12 -> 1.6144665 | S13: =O13-P13-R13 -> 1.3375335 | T13: =S13/(1+I35)^B13 -> 1.0413928 | U13: =1/(1+Assumptions!$B$57)^'[1]FCF Model'!T13 -> 1 | V13: =S13*U13 -> 1.3375335 | X13: 3
A14: 2006 | B14: 4 | C14: 69.81 | D14: 45.41 | E14: 13.3 | F14: 2.9 | G14: =C14-D14-E14-F14 -> 8.2 | H14: =G14*Assumptions!$B$56 -> 3.28 | I14: =G14-H14 -> 4.92 | J14: =F14 -> 2.9 | K14: -3.8 | L14: 10.2 | M14: 14 | N14: 2.5 | O14: =I14+J14 -> 7.82 | P14: 3.8 | Q14: =C14*H2 -> 30.297288 | R14: =Q14-Q13 -> 1.7142857 | S14: =O14-P14-R14 -> 2.3057143 | T14: =S14/(1+I35)^B14 -> 1.6515259 | U14: =1/(1+Assumptions!$B$57)^'[1]FCF Model'!T14 -> 1 | V14: =S14*U14 -> 2.3057143 | X14: 4
A15: 2007 | B15: 5 | C15: 69.81 | D15: 45.41 | E15: 13.3 | F15: 2.9 | G15: =C15-D15-E15-F15 -> 8.2 | H15: =G15*Assumptions!$B$56 -> 3.28 | I15: =G15-H15 -> 4.92 | J15: =F15 -> 2.9 | K15: -2.9 | L15: 10.2 | M15: 14 | N15: 2.5 | O15: =I15+J15 -> 7.82 | P15: 2.9 | Q15: =C15*H2 -> 30.297288 | R15: - | S15: =O15-P15 -> 4.92 | T15: =S15/(1+I35)^B15 -> 3.2420147 | U15: =1/(1+Assumptions!$B$57)^'[1]FCF Model'!T15 -> 1 | V15: =S15*U15 -> 4.92 | X15: 5
A16: Terminal Value | B16: 5 | S16: =S15/(I35-E2) -> 73.431521 | T16: =S16/(1+I35)^B16 -> 48.387413 | V16: =S16/(1+I35)^B15 -> 48.387413
A17: PV | T17: =SUM(T11:T16) -> 54.466198
U18: Debt | V18: =T17*0.37 -> 20.152493
U19: Cash | V19: 1
U20: Net Debt | V20: =V18-V19 -> 19.152493
G21: WACC CALCULATION | U21: Add: Cash | V21: 1
U22: Equity Value | V22: =T17-V20 -> 35.313705
U23: O/s Shares | V23: 0.584
U24: Value per Share | V24: =V22/V23 -> 60.468672
H25: Beta of Asset | I25: =(0.71+0.63+0.8+0.63+0.85+0.73)/6 -> 0.725
H26: D | I26: 0.37
H27: E | I27: 0.63
H28: D/E | I28: =I26/I27 -> 0.58730159
H29: Beta Equity | I29: =I25*(1+I28) -> 1.1507937 | J29: Assume Beta of Debt is 0
H30: RF | I30: 0.041
H31: MP | I31: 0.06
H32: rE | I32: =I30+(I29*(I31)) -> 0.11004762
H33: Tax | I33: 0.4 | K33: 0.0796
H34: Rd | I34: 0.0796
H35: WACC | I35: =(I27*I32)+(I26*I34*(1-I33)) -> 0.0870012

Sheet Sensitivity
B4: TERMINAL Growth | C4: 0.02 | E4: NWC/Sales | F4: =FCF!Q10/FCF!C10 -> 0.43399638
B5: SALES GROWTH | C5: 0.06
A9: SENSITIVITY ANALYSIS
A14: COGS SCENARIO TABLE FOR R.T.C. INC. | H14: reference | I14: 3
B16: 2002 | C16: 2003 | D16: 2004 | E16: 2005 | F16: 2006 | G16: 2007
A17: BEST PERFORMNANCE | B17: =B18-1% -> 0.66535262 | C17: =C18-1% -> 0.65918089 | D17: =D18-1% -> 0.64988728 | E17: =E18-1% -> 0.64009105 | F17: =F18-1% -> 0.6304298 | G17: =G18-1% -> 0.6304298
A18: GOOD PERFORMANCE | B18: =B19-1% -> 0.67535262 | C18: =C19-1% -> 0.66918089 | D18: =D19-1% -> 0.65988728 | E18: =E19-1% -> 0.65009105 | F18: =F19-1% -> 0.6404298 | G18: =G19-1% -> 0.6404298
A19: BASE CASE PERFORMANCE | B19: =(37.9/55.3) -> 0.68535262 | C19: =39.8/58.6 -> 0.67918089 | D19: =41.6/62.1 -> 0.66988728 | E19: =43.5/65.9 -> 0.66009105 | F19: =45.4/69.8 -> 0.6504298 | G19: =45.4/69.8 -> 0.6504298
A20: BAD PERFORMANCE | B20: =B19+1% -> 0.69535262 | C20: =C19+1% -> 0.68918089 | D20: =D19+1% -> 0.67988728 | E20: =E19+1% -> 0.67009105 | F20: =F19+1% -> 0.6604298 | G20: =G19+1% -> 0.6604298
A21: WORST PERFORMANCE | B21: =B20+1% -> 0.70535262 | C21: =C20+1% -> 0.69918089 | D21: =D20+1% -> 0.68988728 | E21: =E20+1% -> 0.68009105 | F21: =F20+1% -> 0.6704298 | G21: =G20+1% -> 0.6704298
A24: SGA SCENARIO TABLE FOR R.T.C. INC. | H24: reference | I24: 3
B26: 2002 | C26: 2003 | D26: 2004 | E26: 2005 | F26: 2006 | G26: 2007
A27: BEST PERFORMNANCE | B27: =B28-1% -> 0.20242315 | C27: =C28-1% -> 0.18989761 | D27: =D28-1% -> 0.17967794 | E27: =E28-1% -> 0.18128824 | F27: =F28-1% -> 0.17054441 | G27: =G28-1% -> 0.17054441
A28: GOOD PERFORMANCE | B28: =B29-1% -> 0.21242315 | C28: =C29-1% -> 0.19989761 | D28: =D29-1% -> 0.18967794 | E28: =E29-1% -> 0.19128824 | F28: =F29-1% -> 0.18054441 | G28: =G29-1% -> 0.18054441
A29: BASE CASE PERFORMANCE | B29: =12.3/55.3 -> 0.22242315 | C29: =12.3/58.6 -> 0.20989761 | D29: =12.4/62.1 -> 0.19967794 | E29: =12.5/62.1 -> 0.20128824 | F29: =13.3/69.8 -> 0.19054441 | G29: =13.3/69.8 -> 0.19054441
A30: BAD PERFORMANCE | B30: =B29+1% -> 0.23242315 | C30: =C29+1% -> 0.21989761 | D30: =D29+1% -> 0.20967794 | E30: =E29+1% -> 0.21128824 | F30: =F29+1% -> 0.20054441 | G30: =G29+1% -> 0.20054441
A31: WORST PERFORMANCE | B31: =B30+1% -> 0.24242315 | C31: =C30+1% -> 0.22989761 | D31: =D30+1% -> 0.21967794 | E31: =E30+1% -> 0.22128824 | F31: =F30+1% -> 0.21054441 | G31: =G30+1% -> 0.21054441
B35: SHARE PRICE SENSITIVITY ANALYSIS - WACC vs TERMINAL GROWTH
C38: TERMINAL GROWTH
B39: 60.48 | C39: 0 | D39: 0.01 | E39: 0.02 | F39: 0.03 | G39: 0.04 | H39: 0.05 | I39: 0.06 | J39: 0.065
A40: WACC | B40: 0.075 | C40: 57.904593 | D40: 65.490403 | E40: 75.83469 | F40: 90.776438 | G40: 114.25633 | H40: 156.52013 | I40: 255.13566 | J40: 378.40508
B41: 0.08 | C41: 53.623172 | D41: 60.075436 | E41: 68.678454 | F41: 80.72268 | G41: 98.789019 | H41: 128.89958 | I41: 189.12071 | J41: 249.34184
B42: 0.085 | C42: 49.859847 | D42: 55.39832 | E42: 62.640939 | F42: 72.517237 | G42: 86.783001 | H42: 109.20063 | I42: 149.55236 | J42: 184.86013
B43: 0.087 | C43: 48.479495 | D43: 53.701788 | E43: 60.482974 | F43: 69.643524 | G43: 82.70218 | H43: 102.81957 | I43: 137.83873 | J43: 167.28666
B44: 0.09 | C44: 46.527925 | D44: 51.320334 | E44: 57.482004 | F44: 65.697563 | G44: 77.199346 | H44: 94.452021 | I44: 123.20648 | J44: 146.21005
B45: 0.095 | C45: 43.55897 | D45: 47.735405 | E45: 53.025557 | F45: 59.943448 | G45: 69.376936 | H45: 83.003084 | I45: 104.4156 | J45: 120.47499
B46: 0.1 | C46: 40.898245 | D46: 44.561043 | E46: 49.139541 | F46: 55.026181 | G46: 62.875034 | H46: 73.863428 | I46: 90.34602 | J46: 102.1193
B49: SHARE PRICE SENSITIVITY ANALYSIS - COST OF EQUITY AND COST OF DEBT
C52: COST OF DEBT
A53: COST OF EQUITY | B53: 60.48 | C53: 0.07 | D53: 0.075 | E53: 0.0796 | F53: 0.08 | G53: 0.085 | H53: 0.09
B54: 0.1 | C54: 70.639652 | D54: 69.139705 | E54: 67.809057 | F54: 67.695499 | G54: 66.304031 | H54: 64.962505
B55: 0.105 | C55: 66.526211 | D55: 65.176768 | E55: 63.977514 | F55: 63.875077 | G55: 62.618688 | H55: 61.405316
B56: 0.11 | C56: 62.819447 | D56: 61.599247 | E56: 60.513115 | F56: 60.420265 | G56: 59.280482 | H56: 58.178011
B57: 0.115 | C57: 59.462729 | D57: 58.35433 | E57: 57.36628 | F57: 57.281752 | G57: 56.243317 | H57: 55.237453
B58: 0.12 | C58: 56.409459 | D58: 55.398416 | E58: 54.495956 | F58: 54.418698 | G58: 53.468899 | H58: 52.547698
B61: SHARE PRICE SENSITIVITY ANALYSIS - WACC AND SALES GROWTH
C63: SALES GROWTH
B64: 60.48 | C64: 0.04 | D64: 0.05 | E64: 0.06 | F64: 0.07 | G64: 0.08
A65: WACC | B65: 0.075 | C65: 69.879231 | D65: 72.815608 | E65: 75.83469 | F65: 78.938036 | G65: 82.127219
B66: 0.08 | C66: 63.417824 | D66: 66.01169 | E66: 68.678454 | F66: 71.419489 | G66: 74.236179
B67: 0.085 | C67: 57.964332 | D67: 60.2703 | E67: 62.640939 | F67: 65.077465 | G67: 67.581105
B68: 0.087 | C68: 56.014531 | D68: 58.217881 | E68: 60.482974 | F68: 62.810971 | G68: 65.203042
B69: 0.09 | C69: 53.302454 | D69: 55.363387 | E69: 57.482004 | F69: 59.659387 | G69: 61.896631
B70: 0.095 | C70: 49.273578 | D70: 51.123724 | E70: 53.025557 | F70: 54.980045 | G70: 56.988167
B71: 0.1 | C71: 45.758752 | D71: 47.425901 | E71: 49.139541 | F71: 50.900543 | G71: 52.709785
B74: SHARE PRICE SENSITIVITY ANALYSIS - TERMINAL GROWTH vs COST OF DEBT
C76: COST OF DEBT
B77: 60.48 | C77: 0.07 | D77: 0.075 | E77: 0.0796 | F77: 0.08 | G77: 0.085 | H77: 0.09
A78: TERMINAL GROWTH | B78: 0 | C78: 49.9519 | D78: 49.175175 | E78: 48.478687 | F78: 48.418921 | G78: 47.682362 | H78: 46.964758
B79: 0.01 | C79: 55.511818 | D79: 54.555556 | E79: 53.700797 | F79: 53.62757 | G79: 52.726651 | H79: 51.851658
B80: 0.02 | C80: 62.785908 | D80: 61.56685 | E80: 60.481719 | F80: 60.388954 | G80: 59.250204 | H80: 58.148715
B81: 0.03 | C81: 72.711389 | D81: 71.083073 | E81: 69.641861 | F81: 69.519013 | G81: 68.015527 | H81: 66.569211
B82: 0.04 | C82: 87.060976 | D82: 84.738583 | E82: 82.699837 | F82: 82.526778 | G82: 80.417914 | H82: 78.405036
B83: 0.05 | C83: 109.6409 | D83: 105.9847 | E83: 102.81595 | F83: 102.54871 | G83: 99.313698 | H83: 96.262649
B84: 0.06 | C84: 150.37918 | D84: 143.58658 | E84: 137.83222 | F84: 137.35242 | G84: 131.61075 | H84: 126.3056
B87: SHARE PRICE SENSITIVITY ANALYSIS - COGS vs TERMINAL GROWTH
C89: TERMINAL GROWTH
B90: 60.48 | C90: 0 | D90: 0.01 | E90: 0.02 | F90: 0.03 | G90: 0.04 | H90: 0.05 | I90: 0.06
A91: BEST PERFORMNANCE | B91: 1 | C91: 58.609379 | D91: 64.720454 | E91: 72.655699 | F91: 83.375181 | G91: 98.656029 | H91: 122.19653 | I91: 163.17366
A92: GOOD PERFORMANCE | B92: 2 | C92: 53.544033 | D92: 59.210626 | E92: 66.568709 | F92: 76.508521 | G92: 90.677933 | H92: 112.50624 | I92: 150.50294
A93: BASE CASE PERFORMANCE | B93: 3 | C93: 48.478687 | D93: 53.700797 | E93: 60.481719 | F93: 69.641861 | G93: 82.699837 | H93: 102.81595 | I93: 137.83222
A94: BAD PERFORMANCE | B94: 4 | C94: 43.413341 | D94: 48.190969 | E94: 54.394729 | F94: 62.775201 | G94: 74.721741 | H94: 93.12566 | I94: 125.16151
A95: WORST PERFORMANCE | B95: 5 | C95: 38.347994 | D95: 42.68114 | E95: 48.307739 | F95: 55.908541 | G95: 66.743645 | H95: 83.435371 | I95: 112.49079
B98: SHARE PRICE SENSITIVITY ANALYSIS - SGA vs WACC
C100: WACC
B101: 60.48 | C101: 0.075 | D101: 0.08 | E101: 0.087 | F101: 0.09 | G101: 0.095 | H101: 0.1 | I101: 0.105
A102: BEST PERFORMNANCE | B102: 1 | C102: 90.675161 | D102: 82.27839 | E102: 72.657173 | F102: 69.132448 | G102: 63.896173 | H102: 59.327788 | I102: 55.309122
A103: GOOD PERFORMANCE | B103: 2 | C103: 83.254926 | D103: 75.478422 | E103: 66.570074 | F103: 63.307226 | G103: 58.460865 | H103: 54.233665 | I103: 50.51605
A104: BASE CASE PERFORMANCE | B104: 3 | C104: 75.83469 | D104: 68.678454 | E104: 60.482974 | F104: 57.482004 | G104: 53.025557 | H104: 49.139541 | I104: 45.722979
A105: BAD PERFORMANCE | B105: 4 | C105: 68.414455 | D105: 61.878486 | E105: 54.395875 | F105: 51.656782 | G105: 47.590249 | H105: 44.045417 | I105: 40.929907
A106: WORST PERFORMANCE | B106: 5 | C106: 60.994219 | D106: 55.078518 | E106: 48.308775 | F106: 45.831559 | G106: 42.154942 | H106: 38.951293 | I106: 36.136836
B109: SHARE PRICE SENSITIVITY ANALYSIS - COGS vs WACC
C112: WACC
B113: 60.48 | C113: 0.075 | D113: 0.08 | E113: 0.087 | F113: 0.09 | G113: 0.095 | H113: 0.1 | I113: 0.105
A114: BEST PERFORMNANCE | B114: 1 | C114: 90.675161 | D114: 82.27839 | E114: 72.657173 | F114: 69.132448 | G114: 63.896173 | H114: 59.327788 | I114: 55.309122
A115: GOOD PERFORMANCE | B115: 2 | C115: 83.254926 | D115: 75.478422 | E115: 66.570074 | F115: 63.307226 | G115: 58.460865 | H115: 54.233665 | I115: 50.51605
A116: BASE CASE PERFORMANCE | B116: 3 | C116: 75.83469 | D116: 68.678454 | E116: 60.482974 | F116: 57.482004 | G116: 53.025557 | H116: 49.139541 | I116: 45.722979
A117: BAD PERFORMANCE | B117: 4 | C117: 68.414455 | D117: 61.878486 | E117: 54.395875 | F117: 51.656782 | G117: 47.590249 | H117: 44.045417 | I117: 40.929907
A118: WORST PERFORMANCE | B118: 5 | C118: 60.994219 | D118: 55.078518 | E118: 48.308775 | F118: 45.831559 | G118: 42.154942 | H118: 38.951293 | I118: 36.136836
B121: SHARE PRICE SENSITIVITY ANALYSIS - SGA vs SALES GROWTH
C123: SALES GROWTH
B124: 60.48 | C124: 0.04 | D124: 0.05 | E124: 0.06 | F124: 0.07 | G124: 0.08
A125: BEST PERFORMNANCE | B125: 1 | C125: 67.36863 | D125: 69.975749 | E125: 72.655699 | F125: 75.409847 | G125: 78.239571
A126: GOOD PERFORMANCE | B126: 2 | C126: 61.691013 | D126: 64.096218 | E126: 66.568709 | F126: 69.10975 | G126: 71.720615
A127: BASE CASE PERFORMANCE | B127: 3 | C127: 56.013396 | D127: 58.216687 | E127: 60.481719 | F127: 62.809653 | G127: 65.201659
A128: BAD PERFORMANCE | B128: 4 | C128: 50.335779 | D128: 52.337156 | E128: 54.394729 | F128: 56.509556 | G128: 58.682702
A129: WORST PERFORMANCE | B129: 5 | C129: 44.658163 | D129: 46.457624 | E129: 48.307739 | F129: 50.209459 | G129: 52.163746
B132: SHARE PRICE SENSITIVITY ANALYSIS - COGS vs SALES GROWTH
C134: SALES GROWTH
B135: 60.48 | C135: 0.04 | D135: 0.05 | E135: 0.06 | F135: 0.07 | G135: 0.08
A136: BEST PERFORMNANCE | B136: 1 | C136: 67.36863 | D136: 69.975749 | E136: 72.655699 | F136: 75.409847 | G136: 78.239571
A137: GOOD PERFORMANCE | B137: 2 | C137: 61.691013 | D137: 64.096218 | E137: 66.568709 | F137: 69.10975 | G137: 71.720615
A138: BASE CASE PERFORMANCE | B138: 3 | C138: 56.013396 | D138: 58.216687 | E138: 60.481719 | F138: 62.809653 | G138: 65.201659
A139: BAD PERFORMANCE | B139: 4 | C139: 50.335779 | D139: 52.337156 | E139: 54.394729 | F139: 56.509556 | G139: 58.682702
A140: WORST PERFORMANCE | B140: 5 | C140: 44.658163 | D140: 46.457624 | E140: 48.307739 | F140: 50.209459 | G140: 52.163746
B143: SHARE PRICE SENSITIVITY ANALYSIS - COGS vs SGA
C145: SGA
C146: BEST | D146: GOOD | E146: BASE | F146: BAD | G146: WORST
B147: 60.48 | C147: 1 | D147: 2 | E147: 3 | F147: 4 | G147: 5
A148: BEST PERFORMNANCE | B148: 1 | C148: 84.829679 | D148: 78.742689 | E148: 72.655699 | F148: 66.568709 | G148: 60.481719
...

Sheet Price Recommendation
A1: Price Recommendation
A3: DCF Valuation Results
A4: Enterprise Value ($ millions) | B4: =FCF!V22+FCF!V20 -> 54.466198
A5: Equity Value ($ millions) | B5: =FCF!V22 -> 35.313705
A6: Price per Share (DCF) | B6: =FCF!V24 -> 60.468672
A8: EBIAT Multiple Valuation
A9: EBIAT Multiple | B9: 13.5
A10: EBIAT (2003, $ millions) | B10: =FCF!I11 -> 2.526
A11: Enterprise Value ($ millions) | B11: =B10*B9 -> 34.101
A12: Equity Value ($ millions) | B12: =B11-FCF!V20 -> 14.948507
A13: Price per Share (EBIAT Multiple) | B13: =B11/Assumptions!B59*1000000 -> 58.392123
A15: Sensitivity Analysis Results
A16: Minimum Price | B16: =MIN(Sensitivity!C65:G71) -> 45.758752
A17: Maximum Price | B17: =MAX(Sensitivity!C65:G71) -> 82.127219
A18: Average Price | B18: =AVERAGE(Sensitivity!C65:G71) -> 61.104326
A20: Final Price Recommendation
A21: Recommended Price per Share | B21: =B18 -> 61.104326
